<?xml version="1.0" encoding="utf-8"?>
<UPGRADE_BARS>
	<!-- TEAM BARS - shared by all classes -->
	<UPGRADE_BAR strUID="TEAM_LOGISTICS" nTotalPoints="12" nMemorySlot="0" strID_name="LOGISTICS" strID_desc="BAR_S1_LOGISTICS">
		<UPGRADE_PERK ID="UPGRADE_PERK_DOUBLE_GEAR" nPointsPrice="3" nIconIdx="1" strID_desc="PERK_DOUBLE_GEAR" />
		<UPGRADE_PERK ID="UPGRADE_PERK_NOMEX_SUIT" nPointsPrice="6" nIconIdx="2" strID_desc="PERK_NOMEX_SUITS" />
		<UPGRADE_PERK ID="UPGRADE_PERK_DOUBLE_MEDIKITS" nPointsPrice="9" nIconIdx="3" strID_desc="PERK_DOUBLE_MEDIKITS" />
		<UPGRADE_PERK ID="UPGRADE_PERK_EXTRA_SP_SLOTS" nPointsPrice="12" nIconIdx="70" strID_desc="PERK_EXTRA_SP_SLOTS" />
	</UPGRADE_BAR>
	<UPGRADE_BAR strUID="TEAM_PHYSICAL" nTotalPoints="12" nMemorySlot="1" strID_name="PHYSICAL" strID_desc="BAR_S2_PHYSICAL">
		<UPGRADE_PERK ID="UPGRADE_PERK_MELEE_DEFENSE" nPointsPrice="2" nIconIdx="4" strID_desc="PERK_MELEE_DEFENSE" />
		<UPGRADE_PERK ID="UPGRADE_PERK_SPEED_INCREASE" nPointsPrice="5" nIconIdx="5" strID_desc="PERK_SPEED_IS_LIFE" />
		<UPGRADE_PERK ID="UPGRADE_PERK_MULE" nPointsPrice="7" nIconIdx="6" strID_desc="PERK_MULE" />
		<UPGRADE_PERK ID="UPGRADE_PERK_DIE_HARD" nPointsPrice="12" nIconIdx="7" strID_desc="PERK_DIE_HARD" />
	</UPGRADE_BAR>
	<!-- CLASS BARS - SPECIFIC TO ASSAULTER -->
	<UPGRADE_BAR strUID="A1_ACCURACY" nTotalPoints="12" nMemorySlot="2" strID_name="ACCURACY" strID_desc="BAR_A1_ACCURACY">
		<UPGRADE_PERK ID="UPGRADE_PERK_QUICK_AIM" nPointsPrice="3" nIconIdx="8" strID_desc="PERK_QUICK_AIM" />
		<UPGRADE_PERK ID="UPGRADE_PERK_CRITICAL_SHOTS" nPointsPrice="7" nIconIdx="9" strID_desc="PERK_CRITICAL_SHOTS" />
		<UPGRADE_PERK ID="UPGRADE_PERK_SUREFOOTED" nPointsPrice="12" nIconIdx="10" strID_desc="PERK_SUREFOOTED" />
	</UPGRADE_BAR>
	<UPGRADE_BAR strUID="A2_RECOIL" nTotalPoints="12" nMemorySlot="3" strID_name="RECOIL" strID_desc="BAR_A2_RECOIL">
		<UPGRADE_PERK ID="UPGRADE_PERK_BARRICADE" nPointsPrice="2" nIconIdx="12" strID_desc="PERK_BARRICADE_SHOOTING" />
		<UPGRADE_PERK ID="UPGRADE_PERK_STRONG_STANCE" nPointsPrice="8" nIconIdx="14" strID_desc="PERK_STRONG_STANCE" />
		<UPGRADE_PERK ID="UPGRADE_PERK_C_CLAMP" nPointsPrice="12" nIconIdx="15" strID_desc="PERK_C_CLAMP" />
	</UPGRADE_BAR>
	<UPGRADE_BAR strUID="A3_TACTICS" nTotalPoints="12" nMemorySlot="4" strID_name="TACTICS" strID_desc="BAR_NO_IMPROVEMENT">
		<UPGRADE_PERK ID="UPGRADE_PERK_DOUBLE_BANGERS" nPointsPrice="4" nIconIdx="16" strID_desc="PERK_DOUBLE_BANGERS" />
		<UPGRADE_PERK ID="UPGRADE_PERK_INTIMIDATING" nPointsPrice="7" nIconIdx="17" strID_desc="PERK_INTIMIDATING" />
		<UPGRADE_PERK ID="UPGRADE_PERK_ASSAULT_JUMP" nPointsPrice="12" nIconIdx="52" strID_desc="PERK_ASSAULT_JUMP" />
	</UPGRADE_BAR>
	<!-- CLASS BARS - SPECIFIC TO BREACHER -->
	<UPGRADE_BAR strUID="B1_RECOIL" nTotalPoints="12" nMemorySlot="5" strID_name="BREACH_RECOIL" strID_desc="BAR_B1_RECOIL">
		<UPGRADE_PERK ID="UPGRADE_PERK_TWIN_SHOT" nPointsPrice="4" nIconIdx="20" strID_desc="PERK_TWIN_SHOT" />
		<UPGRADE_PERK ID="UPGRADE_PERK_9PELLET_BUCK" nPointsPrice="7" nIconIdx="21" strID_desc="PERK_9_PELLET" />
		<UPGRADE_PERK ID="UPGRADE_PERK_KILLING_SPREE" nPointsPrice="12" nIconIdx="22" strID_desc="PERK_KILLING_SPREE" />
	</UPGRADE_BAR>
	<UPGRADE_BAR strUID="B2_RELOAD" nTotalPoints="12" nMemorySlot="6" strID_name="BREACH_RELOAD" strID_desc="BAR_B2_RELOAD">
		<UPGRADE_PERK ID="UPGRADE_PERK_EXTENSION_TUBES" nPointsPrice="4" nIconIdx="56" strID_desc="PERK_EXTENSION_TUBES" />
		<UPGRADE_PERK ID="UPGRADE_PERK_RIFLED_SLUGS" nPointsPrice="8" nIconIdx="25" strID_desc="PERK_RIFLED_SLUGS" />
		<UPGRADE_PERK ID="UPGRADE_PERK_IMPROVED_SLUGS" nPointsPrice="12" nIconIdx="26" strID_desc="PERK_IMPROVED_SLUGS" />
	</UPGRADE_BAR>
	<UPGRADE_BAR strUID="B3_TACTICS" nTotalPoints="12" nMemorySlot="7" strID_name="TACTICS" strID_desc="BAR_NO_IMPROVEMENT">
		<UPGRADE_PERK ID="UPGRADE_PERK_GORE_DEALER" nPointsPrice="3" nIconIdx="28" strID_desc="PERK_GORE_DEALER" />
		<UPGRADE_PERK ID="UPGRADE_PERK_POINTMAN_ARMOR" nPointsPrice="7" nIconIdx="29" strID_desc="PERK_POINTMAN_ARMOR" />
		<UPGRADE_PERK ID="UPGRADE_PERK_WEAK_SPOTTER" nPointsPrice="12" nIconIdx="30" strID_desc="PERK_WEAK_SPOTTER" />
	</UPGRADE_BAR>
	<!-- CLASS BARS - SPECIFIC TO SHIELD -->
	<UPGRADE_BAR strUID="S1_HANDGUN" nTotalPoints="12" nMemorySlot="8" strID_name="SHIELD_HANDGUN" strID_desc="BAR_S1_HANDGUN">
		<UPGRADE_PERK ID="UPGRADE_PERK_EXTENDED_MAGS" nPointsPrice="2" nIconIdx="63" strID_desc="PERK_EXTENDED_MAGS" />
		<UPGRADE_PERK ID="UPGRADE_PERK_SHIELD_BRACE" nPointsPrice="6" nIconIdx="40" strID_desc="PERK_SHIELD_BRACE" />
		<UPGRADE_PERK ID="UPGRADE_PERK_LADY_JUSTICE" nPointsPrice="12" nIconIdx="49" strID_desc="PERK_LADY_JUSTICE" />
	</UPGRADE_BAR>
	<UPGRADE_BAR strUID="S2_SHIELD" nTotalPoints="12" nMemorySlot="9" strID_name="SHIELD_SHIELD" strID_desc="BAR_S2_SHIELD_USE">
		<UPGRADE_PERK ID="UPGRADE_PERK_FORTIFIED" nPointsPrice="3" nIconIdx="45" strID_desc="PERK_FORTIFIED" />
		<UPGRADE_PERK ID="UPGRADE_PERK_ARMORED_RABBIT" nPointsPrice="6" nIconIdx="41" strID_desc="PERK_ARMORED_RABBIT" />
		<UPGRADE_PERK ID="UPGRADE_PERK_FIELD_FIXER" nPointsPrice="12" nIconIdx="64" strID_desc="PERK_FIELD_FIXER" />
	</UPGRADE_BAR>
	<UPGRADE_BAR strUID="S3_TACTICS" nTotalPoints="12" nMemorySlot="10" strID_name="TACTICS" strID_desc="BAR_NO_IMPROVEMENT">
		<UPGRADE_PERK ID="UPGRADE_PERK_DEVASTATOR" nPointsPrice="4" nIconIdx="65" strID_desc="PERK_DEVASTATOR" />
		<UPGRADE_PERK ID="UPGRADE_PERK_CADDYSHACK" nPointsPrice="8" nIconIdx="58" strID_desc="PERK_CADDYSHACK" />
		<UPGRADE_PERK ID="UPGRADE_PERK_IRON_MAN" nPointsPrice="12" nIconIdx="51" strID_desc="PERK_IRON_MAN" />
	</UPGRADE_BAR>
	<!-- CLASS BARS - SPECIFIC TO RECON -->
	<UPGRADE_BAR strUID="R1_GUNPLAY" nTotalPoints="12" nMemorySlot="11" strID_name="ACCURACY" strID_desc="BAR_R1_GUNPLAY">
		<UPGRADE_PERK ID="UPGRADE_PERK_HANDYMAN" nPointsPrice="2" nIconIdx="67" strID_desc="PERK_HANDYMAN" />
		<UPGRADE_PERK ID="UPGRADE_PERK_DISORIENTED" nPointsPrice="6" nIconIdx="68" strID_desc="PERK_DISORIENTED" />
		<UPGRADE_PERK ID="UPGRADE_PERK_CRIPPLING_SHOTS" nPointsPrice="9" nIconIdx="55" strID_desc="PERK_CRIPPLING_SHOTS" />
		<UPGRADE_PERK ID="UPGRADE_PERK_SURGEON_PRECISION" nPointsPrice="12" nIconIdx="57" strID_desc="PERK_SURGEON_PRECISION" />
	</UPGRADE_BAR>
	<UPGRADE_BAR strUID="R2_RECON" nTotalPoints="12" nMemorySlot="12" strID_name="RECON" strID_desc="BAR_R2_RECON">
		<UPGRADE_PERK ID="UPGRADE_PERK_INVISIBLE" nPointsPrice="4" nIconIdx="62" strID_desc="PERK_INVISIBLE" />
		<UPGRADE_PERK ID="UPGRADE_PERK_DURACELLS" nPointsPrice="7" nIconIdx="50" strID_desc="PERK_DURACELLS" />
		<UPGRADE_PERK ID="UPGRADE_PERK_RESCUE_PLAN" nPointsPrice="12" nIconIdx="54" strID_desc="PERK_RESCUE_PLAN" />
	</UPGRADE_BAR>
	<UPGRADE_BAR strUID="R3_TACTICS" nTotalPoints="12" nMemorySlot="13" strID_name="TACTICS" strID_desc="BAR_NO_IMPROVEMENT">
		<UPGRADE_PERK ID="UPGRADE_PERK_EXTENDED_MAGS_RECON" nPointsPrice="3" nIconIdx="63" strID_desc="PERK_EXTENDED_MAGS_RECON" />
		<UPGRADE_PERK ID="UPGRADE_PERK_VULTURE" nPointsPrice="6" nIconIdx="59" strID_desc="PERK_VULTURE" />
		<UPGRADE_PERK ID="UPGRADE_PERK_DOUBLE_TOOLS" nPointsPrice="9" nIconIdx="60" strID_desc="PERK_DOUBLE_TOOLS" />
		<UPGRADE_PERK ID="UPGRADE_PERK_CAUGHT_IN_THE_ACT" nPointsPrice="12" nIconIdx="48" strID_desc="PERK_CAUGHT_IN_THE_ACT" />
	</UPGRADE_BAR>
	<!-- CLASS BARS - SPECIFIC TO FERGIE -->
	<UPGRADE_BAR strUID="F1_HANDGUN" nTotalPoints="12" nMemorySlot="14" strID_name="FERGIE_HANDGUN" strID_desc="BAR_F1_HANDGUN">
		<UPGRADE_PERK ID="UPGRADE_PERK_STEADY_HAND" nPointsPrice="3" nIconIdx="32" strID_desc="PERK_STEADY_HAND" />
		<UPGRADE_PERK ID="UPGRADE_PERK_WEAVER_STANCE" nPointsPrice="6" nIconIdx="31" strID_desc="PERK_WEAVER_STANCE" />
		<UPGRADE_PERK ID="UPGRADE_PERK_EXTENDED_MAGS" nPointsPrice="9" nIconIdx="63" strID_desc="PERK_EXTENDED_MAGS" />
		<UPGRADE_PERK ID="UPGRADE_PERK_HOLLOW_POINTS" nPointsPrice="12" nIconIdx="66" strID_desc="PERK_HOLLOW_POINTS" />
	</UPGRADE_BAR>
	<UPGRADE_BAR strUID="F2_MELEE" nTotalPoints="12" nMemorySlot="15" strID_name="FERGIE_MELEE" strID_desc="BAR_F2_MELEE">
		<UPGRADE_PERK ID="UPGRADE_PERK_COMBATIVES" nPointsPrice="3" nIconIdx="35" strID_desc="PERK_COMBATIVES" />
		<UPGRADE_PERK ID="UPGRADE_PERK_LEG_DAY" nPointsPrice="7" nIconIdx="36" strID_desc="PERK_LEG_DAY" />
		<UPGRADE_PERK ID="UPGRADE_PERK_FEDERAL_JUSTICE" nPointsPrice="12" nIconIdx="38" strID_desc="PERK_FEDERAL_JUSTICE" />
	</UPGRADE_BAR>
	<UPGRADE_BAR strUID="F3_BUREAUCRACY" nTotalPoints="12" nMemorySlot="16" strID_name="FERGIE_BUREAUCRACY" strID_desc="BAR_NO_IMPROVEMENT">
		<UPGRADE_PERK ID="UPGRADE_PERK_EVASION" nPointsPrice="5" nIconIdx="39" strID_desc="PERK_EVASION" />
		<UPGRADE_PERK ID="UPGRADE_PERK_BIG_BANGER" nPointsPrice="9" nIconIdx="53" strID_desc="PERK_BIG_BANGER" />
		<UPGRADE_PERK ID="UPGRADE_PERK_CHERRY_DARLING" nPointsPrice="12" nIconIdx="61" strID_desc="PERK_CHERRY_DARLING" />
	</UPGRADE_BAR>
	<!-- CLASS BARS - SPECIFIC TO OFF-DUTY GUY-->
	<UPGRADE_BAR strUID="O1_SHOOTING" nTotalPoints="12" nMemorySlot="17" strID_name="ACCURACY" strID_desc="BAR_O1_ACCURACY">
		<UPGRADE_PERK ID="UPGRADE_PERK_SOFT_POINTS" nPointsPrice="2" nIconIdx="71" strID_desc="PERK_SOFT_POINTS" />
		<UPGRADE_PERK ID="UPGRADE_PERK_P_AMMO" nPointsPrice="7" nIconIdx="72" strID_desc="PERK_PLUSP_AMMO" />
		<UPGRADE_PERK ID="UPGRADE_PERK_OPEN_SEASON" nPointsPrice="12" nIconIdx="73" strID_desc="PERK_OPEN_SEASON" />
	</UPGRADE_BAR>
	<UPGRADE_BAR strUID="O2_FITNESS" nTotalPoints="12" nMemorySlot="18" strID_name="FITNESS" strID_desc="BAR_O2_MELEE">
		<UPGRADE_PERK ID="UPGRADE_PERK_REDHEAD" nPointsPrice="4" nIconIdx="74" strID_desc="PERK_REDHEAD" />
		<UPGRADE_PERK ID="UPGRADE_PERK_GRIZZLY" nPointsPrice="8" nIconIdx="75" strID_desc="PERK_GRIZZLY" />
		<UPGRADE_PERK ID="UPGRADE_PERK_LOCKED_OUT" nPointsPrice="12" nIconIdx="76" strID_desc="PERK_LOCKED_OUT" />
	</UPGRADE_BAR>
	<UPGRADE_BAR strUID="O3_GEAR_BAG" nTotalPoints="12" nMemorySlot="19" strID_name="GEAR_BAG" strID_desc="BAR_NO_IMPROVEMENT">
		<UPGRADE_PERK ID="UPGRADE_PERK_TWIXIE" nPointsPrice="6" nIconIdx="77" strID_desc="PERK_TWIXIE" />
		<UPGRADE_PERK ID="UPGRADE_PERK_PLATES_UPGRADE" nPointsPrice="9" nIconIdx="78" strID_desc="PERK_PLATES_UPGRADE" />
		<UPGRADE_PERK ID="UPGRADE_PERK_GARAND_AP_AMMO" nPointsPrice="12" nIconIdx="79" strID_desc="PERK_GARAND_AP_AMMO" />
	</UPGRADE_BAR>

</UPGRADE_BARS>